netmind_parse_pdf_mcp/__init__.py
netmind_parse_pdf_mcp/server.py
netmind_parse_pdf_mcp-0.1.7.dist-info/LICENSE
netmind_parse_pdf_mcp-0.1.7.dist-info/METADATA
netmind_parse_pdf_mcp-0.1.7.dist-info/WHEEL
netmind_parse_pdf_mcp-0.1.7.dist-info/entry_points.txt
netmind_parse_pdf_mcp-0.1.7.dist-info/RECORD
